MANIFEST.in
README.rst
setup.py
docs/HISTORY.txt
docs/LICENSE.txt
src/collective/__init__.py
src/collective.cmisbrowser.egg-info/PKG-INFO
src/collective.cmisbrowser.egg-info/SOURCES.txt
src/collective.cmisbrowser.egg-info/dependency_links.txt
src/collective.cmisbrowser.egg-info/namespace_packages.txt
src/collective.cmisbrowser.egg-info/not-zip-safe
src/collective.cmisbrowser.egg-info/requires.txt
src/collective.cmisbrowser.egg-info/top_level.txt
src/collective/cmisbrowser/__init__.py
src/collective/cmisbrowser/configure.zcml
src/collective/cmisbrowser/errors.py
src/collective/cmisbrowser/interfaces.py
src/collective/cmisbrowser/browser/__init__.py
src/collective/cmisbrowser/browser/configure.zcml
src/collective/cmisbrowser/browser/forms.py
src/collective/cmisbrowser/browser/icons.py
src/collective/cmisbrowser/browser/settings.py
src/collective/cmisbrowser/browser/urls.py
src/collective/cmisbrowser/browser/viewlets.py
src/collective/cmisbrowser/browser/views.py
src/collective/cmisbrowser/browser/static/CMISBrowser.png
src/collective/cmisbrowser/browser/static/CMISDocument.png
src/collective/cmisbrowser/browser/static/CMISFolder.png
src/collective/cmisbrowser/browser/templates/cmisbrowsererrorview.pt
src/collective/cmisbrowser/browser/templates/cmisbrowserinfoview.pt
src/collective/cmisbrowser/cmis/__init__.py
src/collective/cmisbrowser/cmis/api.py
src/collective/cmisbrowser/cmis/content.py
src/collective/cmisbrowser/cmis/result.py
src/collective/cmisbrowser/connector/__init__.py
src/collective/cmisbrowser/connector/configure.zcml
src/collective/cmisbrowser/connector/rest.py
src/collective/cmisbrowser/connector/soap.py
src/collective/cmisbrowser/content/__init__.py
src/collective/cmisbrowser/content/cmisbrowser.py
src/collective/cmisbrowser/content/configure.zcml
src/collective/cmisbrowser/i18n/collective.cmisbrowser.pot
src/collective/cmisbrowser/i18n/en/LC_MESSAGES/collective.cmisbrowser.mo
src/collective/cmisbrowser/i18n/en/LC_MESSAGES/collective.cmisbrowser.po
src/collective/cmisbrowser/i18n/fr/LC_MESSAGES/collective.cmisbrowser.mo
src/collective/cmisbrowser/i18n/fr/LC_MESSAGES/collective.cmisbrowser.po
src/collective/cmisbrowser/i18n/nl/LC_MESSAGES/collective.cmisbrowser.mo
src/collective/cmisbrowser/i18n/nl/LC_MESSAGES/collective.cmisbrowser.po
src/collective/cmisbrowser/profiles/default/controlpanel.xml
