Metadata-Version: 1.1
Name: collective.cmisbrowser
Version: 1.0
Summary: CMIS repository browser for Plone
Home-page: http://pypi.python.org/pypi/collective.cmisbrowser
Author: Sylvain Viollon
Author-email: sylvain@infrae.com
License: GPL
Keywords: CMIS connection browser plone
Platform: UNKNOWN
Classifier: Framework :: Plone
Classifier: Framework :: Zope2
